{
  "categorias": [
    {
      "titulo": "Tives-Cast",
      "link": "https://www.youtube.com/watch?v=Q93yNPfnwTw&feature=youtu.be",
      "cor": "red",
      "link_extra": {
        "text": "O PodCast Mais inusitado esta chegando",
        "url": "https://www.youtube.com/watch?v=Q93yNPfnwTw&feature=youtu.be"
      },
      "videos": [
        {
          "titulo": "Os bandidos sempre se dão mal - Game Play spider man PS4",
          "url": "https://www.youtube.com/watch?v=i_i9YR7vScw"
        },
        {
          "titulo": "Teaser teaser TivesCast",
          "url": "https://www.youtube.com/watch?v=Q93yNPfnwTw&feature=youtu.be"
        },
        {
          "titulo": "",
          "url": ""
        },
        {
          "titulo": "",
          "url": ""
        },
        {
          "titulo": "",
          "url": ""
        },
        {
          "titulo": "",
          "url": ""
        },
        {
          "titulo": "",
          "url": ""
        },
        {
          "titulo": "",
          "url": ""
        }        
      ]
    },
    {
      "titulo": "Filmes",
      "cor": "red",
      "link_extra": {
        "text": "Cursos de Back End na Alura",
        "url": "https://www.alura.com.br/cursos-online-programacao"
      },
      "videos": [
        {
          "titulo": "PERCURSO em NÍVEL em ÁRVORE BINÁRIA | Estruturas de Dados #14",
          "url": "https://www.youtube.com/watch?v=UOK7nS2E9xM"
        },
        {
          "titulo": "Coders4Tips - S01E04: GitHub CLI - Uma Nova Experiência no Github!",
          "url": "https://www.youtube.com/watch?v=6o6-bKOZOEY"
        },
        {
          "titulo": "Programei 4 robôs que criam vídeos para mim no YouTube",
          "url": "https://www.youtube.com/watch?v=kjhu1LEmRpY"
        },
        {
          "titulo": "API: Dicionário do Programador",
          "url": "https://www.youtube.com/watch?v=vGuqKIRWosk"
        }, 
        {
          "titulo": "",
          "url": "https://www.youtube.com/watch?v=6OokP-NE49k"
        }
      ]
    },
    {
      "titulo": "Dica de musicas ",
      "cor": "red",
      "link_extra": {
        "text": "Se liga nesses Soms",
        "url": "https://www.youtube.com/watch?v=okpwnSwo_LA"
      },
      "videos": [
        {
          "titulo": "Wild World - Cat Stevens - FUNK cover feat. Rett Madison!!",
          "url": "https://www.youtube.com/watch?v=okpwnSwo_LA"
        },
        {
          "titulo": "Foo Fighters Meets 70's Bobby Caldwell - Live Looping Mashup by Elise Trouw",
          "url": "https://www.youtube.com/watch?v=Gl9GtO_vQxw&list=RDGl9GtO_vQxw&index=7"
        },
        {
          "titulo": "Childish Gambino - Feels Like Summer (Official Music Video)",
          "url": "https://www.youtube.com/watch?v=F1B9Fk_SgI0&feature=youtu.be"
        },
        {
          "titulo": "Post Malone, Swae Lee - Sunflower (Spider-Man: Into the Spider-Verse)",
          "url": "https://www.youtube.com/watch?v=ApXoWvfEYVU&feature=youtu.be"
        },
        {
          "titulo": "The Weeknd - Blinding Lights",
          "url": "https://www.youtube.com/watch?v=4NRXx6U8ABQ"
        },
        {
          "titulo": "The Weeknd - Blinding Lights",
          "url": "https://www.youtube.com/watch?v=FGBhQbmPwH8&feature=youtu.be"
        }
      ]
    },
    {
      "titulo": "Dicas de Filmes do Momento ",
      "cor": "red",
      "link_extra": {
        "text": "Dicas de Filmes do Tives",
        "url": ""
      },
      "videos": [
        {
          "titulo": "Spider-Man-INTO THE SPIDER-VERSE",
          "url": "https://www.youtube.com/watch?v=ii3n7hYQOl4"
        },
        {
          "titulo": "The Secret Life of Walter Mitty ",
          "url": "https://www.youtube.com/watch?v=HddkucqSzSM"
        },
        {
          "titulo": "Yesterday",
          "url": "https://www.youtube.com/watch?v=Yyk9N40uIFs"
        },
        {
          "titulo": "Jumanji Next Level",
          "url": "https://www.youtube.com/watch?v=Gz0lJz_ldRo"
        }
      ]
    },
    {
      "titulo": "Games e Gameplay do Tives",
      "cor": "red",
      "link_extra": {
        "text": "Games e games plays pra você curtir",
        "url": ""
      },
      "videos": [
        {
          "titulo": "Jogando Spider-man PS4",
          "url": "https://www.youtube.com/watch?v=i_i9YR7vScw"
        },
        {
          "titulo": "Game Play- god of war",
          "url": "https://www.youtube.com/watch?v=iiWcaahcn80&t=136s"
        },
        {
          "titulo": "Ori and the blind Forest",
          "url": "https://www.youtube.com/watch?v=cklw-Yu3moE&t=23s"
        },
        {
          "titulo": "Zelda Breath of the wild",
          "url": "https://www.youtube.com/watch?v=zw47_q9wbBE"
        },
        {
          "titulo": "Last Of Us",
          "url": "https://www.youtube.com/watch?v=v5J0Vo_iVs8"
        }
      ]
    },
    {
      "titulo": "Game Play no Xbox-One",
      "cor": "red",
      "link_extra": {
        "text": "Aventuras de um player convencional",
        "url": ""
      },
      "videos": [
        {
          "titulo": "O dia que dei um tiro de sorte no GTAV",
          "url": "https://www.youtube.com/watch?v=olVC7Svx-Qw"
        },
        {
          "titulo": "Se aventurando em Ori and The blind forest",
          "url": "https://www.youtube.com/watch?v=Ss3dmy-mizU"
        },
        {
          "titulo": "Zuando o GTA com o Carlos Santos",
          "url": "https://www.youtube.com/watch?v=hB5Y--DG2IU"
        },
        {
          "titulo": "Sekiro e o Boss",
          "url": "https://www.youtube.com/watch?v=8E80hWo4-C8"
        },
        {
          "titulo": "Na Balada",
          "url": "https://www.youtube.com/watch?v=y2zixEilMQ8"
        }
      ]
    }
  ]
}